{
  "formatVersion": "1.1",
  "component": {
    "group": "com.syncedapps",
    "module": "inthegametv",
    "version": "2.6.20",
    "attributes": {
      "org.gradle.status": "release"
    }
  },
  "createdBy": {
    "gradle": {
      "version": "8.0"
    }
  },
  "variants": [
    {
      "name": "releaseApiElements-published",
      "attributes": {
        "org.gradle.category": "library",
        "org.gradle.usage": "java-api",
        "org.jetbrains.kotlin.platform.type": "androidJvm"
      },
      "dependencies": [
        {
          "group": "com.github.Inthegamesdk",
          "module": "itg-android-storket",
          "version": {
            "requires": "1.0.11"
          }
        },
        {
          "group": "org.jetbrains.kotlin",
          "module": "kotlin-stdlib",
          "version": {
            "requires": "1.8.21"
          }
        },
        {
          "group": "org.jetbrains.kotlin",
          "module": "kotlin-stdlib-jdk7",
          "version": {
            "requires": "1.8.21"
          }
        },
        {
          "group": "org.jetbrains.kotlin",
          "module": "kotlin-stdlib-jdk8",
          "version": {
            "requires": "1.8.21"
          }
        },
        {
          "group": "org.jetbrains.kotlin",
          "module": "kotlin-reflect",
          "version": {
            "requires": "1.8.21"
          }
        },
        {
          "group": "androidx.fragment",
          "module": "fragment-ktx",
          "version": {
            "requires": "1.6.0"
          }
        },
        {
          "group": "androidx.activity",
          "module": "activity-ktx",
          "version": {
            "requires": "1.7.2"
          }
        },
        {
          "group": "androidx.core",
          "module": "core-ktx",
          "version": {
            "requires": "1.10.1"
          }
        },
        {
          "group": "androidx.appcompat",
          "module": "appcompat",
          "version": {
            "requires": "1.6.1"
          }
        },
        {
          "group": "com.google.android.material",
          "module": "material",
          "version": {
            "requires": "1.9.0"
          }
        },
        {
          "group": "androidx.swiperefreshlayout",
          "module": "swiperefreshlayout",
          "version": {
            "requires": "1.1.0"
          }
        },
        {
          "group": "com.squareup.retrofit2",
          "module": "retrofit",
          "version": {
            "requires": "2.9.0"
          },
          "excludes": [
            {
              "group": "com.squareup.okhttp3",
              "module": "okhttp"
            }
          ]
        },
        {
          "group": "com.squareup.retrofit2",
          "module": "converter-gson",
          "version": {
            "requires": "2.9.0"
          }
        },
        {
          "group": "com.google.android.flexbox",
          "module": "flexbox",
          "version": {
            "requires": "3.0.0"
          }
        },
        {
          "group": "com.github.bumptech.glide",
          "module": "glide",
          "version": {
            "requires": "4.14.2"
          }
        },
        {
          "group": "androidx.constraintlayout",
          "module": "constraintlayout",
          "version": {
            "requires": "2.1.4"
          }
        },
        {
          "group": "com.pusher",
          "module": "pusher-java-client",
          "version": {
            "requires": "2.2.6"
          }
        },
        {
          "group": "com.google.zxing",
          "module": "core",
          "version": {
            "requires": "3.5.0"
          }
        },
        {
          "group": "com.localebro",
          "module": "okhttpprofiler",
          "version": {
            "requires": "1.0.8"
          }
        },
        {
          "group": "org.jetbrains.kotlinx",
          "module": "kotlinx-coroutines-core",
          "version": {
            "requires": "1.6.4"
          }
        },
        {
          "group": "org.jetbrains.kotlinx",
          "module": "kotlinx-coroutines-android",
          "version": {
            "requires": "1.6.4"
          }
        },
        {
          "group": "com.squareup.okio",
          "module": "okio",
          "version": {
            "requires": "3.2.0"
          }
        },
        {
          "group": "androidx.room",
          "module": "room-runtime",
          "version": {
            "requires": "2.5.1"
          }
        },
        {
          "group": "androidx.room",
          "module": "room-ktx",
          "version": {
            "requires": "2.5.1"
          }
        },
        {
          "group": "androidx.multidex",
          "module": "multidex",
          "version": {
            "requires": "2.0.1"
          }
        },
        {
          "group": "com.airbnb.android",
          "module": "paris",
          "version": {
            "requires": "2.0.0"
          }
        },
        {
          "group": "com.google.android.exoplayer",
          "module": "exoplayer-core",
          "version": {
            "requires": "2.18.7"
          }
        },
        {
          "group": "com.google.android.exoplayer",
          "module": "exoplayer-dash",
          "version": {
            "requires": "2.18.7"
          }
        },
        {
          "group": "com.google.android.exoplayer",
          "module": "exoplayer-ui",
          "version": {
            "requires": "2.18.7"
          }
        },
        {
          "group": "com.google.android.exoplayer",
          "module": "extension-leanback",
          "version": {
            "requires": "2.18.7"
          }
        },
        {
          "group": "androidx.leanback",
          "module": "leanback",
          "version": {
            "requires": "1.0.0"
          }
        },
        {
          "group": "com.kaltura.player",
          "module": "tvplayer",
          "version": {
            "requires": "4.29.0"
          }
        },
        {
          "group": "com.github.MackHartley",
          "module": "RoundedProgressBar",
          "version": {
            "requires": "3.0.0"
          }
        },
        {
          "group": "androidx.media3",
          "module": "media3-exoplayer",
          "version": {
            "requires": "1.4.1"
          }
        },
        {
          "group": "androidx.media3",
          "module": "media3-exoplayer-dash",
          "version": {
            "requires": "1.4.1"
          }
        },
        {
          "group": "androidx.media3",
          "module": "media3-ui",
          "version": {
            "requires": "1.4.1"
          }
        },
        {
          "group": "com.github.xYinKio",
          "module": "ArcCircleProgressBar",
          "version": {
            "requires": "0.07-alpha"
          }
        },
        {
          "group": "androidx.databinding",
          "module": "viewbinding",
          "version": {
            "requires": "8.1.1"
          }
        },
        {
          "group": "androidx.databinding",
          "module": "databinding-common",
          "version": {
            "requires": "8.1.1"
          }
        },
        {
          "group": "androidx.databinding",
          "module": "databinding-runtime",
          "version": {
            "requires": "8.1.1"
          }
        },
        {
          "group": "androidx.databinding",
          "module": "databinding-adapters",
          "version": {
            "requires": "8.1.1"
          }
        },
        {
          "group": "androidx.databinding",
          "module": "databinding-ktx",
          "version": {
            "requires": "8.1.1"
          }
        }
      ],
      "files": [
        {
          "name": "inthegametv-2.6.20.aar",
          "url": "inthegametv-2.6.20.aar",
          "size": 4976764,
          "sha512": "20014c30f9f2972c742ccae6153dfc328a350c9b168c89de8c579b960b4c42298edd878ca3eb7da74e7e1e8efdd51fb1a2ad6cc3d40d737bded8cd63f48e0b49",
          "sha256": "411fd11f583ea9f6db73fd375340fe1b066677b8f164a66b91b400caa0024d6d",
          "sha1": "92567e21bd616b9db9e4a6cbfd5884b488e99ab6",
          "md5": "54771ab2a96749210a2dc8ae970ae937"
        }
      ]
    },
    {
      "name": "releaseRuntimeElements-published",
      "attributes": {
        "org.gradle.category": "library",
        "org.gradle.usage": "java-runtime",
        "org.jetbrains.kotlin.platform.type": "androidJvm"
      },
      "dependencies": [
        {
          "group": "org.jetbrains.kotlin",
          "module": "kotlin-parcelize-runtime",
          "version": {
            "requires": "1.8.21"
          }
        },
        {
          "group": "com.github.Inthegamesdk",
          "module": "itg-android-storket",
          "version": {
            "requires": "1.0.11"
          }
        },
        {
          "group": "org.jetbrains.kotlin",
          "module": "kotlin-stdlib",
          "version": {
            "requires": "1.8.21"
          }
        },
        {
          "group": "org.jetbrains.kotlin",
          "module": "kotlin-stdlib-jdk7",
          "version": {
            "requires": "1.8.21"
          }
        },
        {
          "group": "org.jetbrains.kotlin",
          "module": "kotlin-stdlib-jdk8",
          "version": {
            "requires": "1.8.21"
          }
        },
        {
          "group": "org.jetbrains.kotlin",
          "module": "kotlin-reflect",
          "version": {
            "requires": "1.8.21"
          }
        },
        {
          "group": "androidx.fragment",
          "module": "fragment-ktx",
          "version": {
            "requires": "1.6.0"
          }
        },
        {
          "group": "androidx.activity",
          "module": "activity-ktx",
          "version": {
            "requires": "1.7.2"
          }
        },
        {
          "group": "androidx.core",
          "module": "core-ktx",
          "version": {
            "requires": "1.10.1"
          }
        },
        {
          "group": "androidx.appcompat",
          "module": "appcompat",
          "version": {
            "requires": "1.6.1"
          }
        },
        {
          "group": "com.google.android.material",
          "module": "material",
          "version": {
            "requires": "1.9.0"
          }
        },
        {
          "group": "androidx.swiperefreshlayout",
          "module": "swiperefreshlayout",
          "version": {
            "requires": "1.1.0"
          }
        },
        {
          "group": "com.squareup.retrofit2",
          "module": "retrofit",
          "version": {
            "requires": "2.9.0"
          },
          "excludes": [
            {
              "group": "com.squareup.okhttp3",
              "module": "okhttp"
            }
          ]
        },
        {
          "group": "com.squareup.retrofit2",
          "module": "converter-gson",
          "version": {
            "requires": "2.9.0"
          }
        },
        {
          "group": "com.google.android.flexbox",
          "module": "flexbox",
          "version": {
            "requires": "3.0.0"
          }
        },
        {
          "group": "com.github.bumptech.glide",
          "module": "glide",
          "version": {
            "requires": "4.14.2"
          }
        },
        {
          "group": "androidx.constraintlayout",
          "module": "constraintlayout",
          "version": {
            "requires": "2.1.4"
          }
        },
        {
          "group": "com.pusher",
          "module": "pusher-java-client",
          "version": {
            "requires": "2.2.6"
          }
        },
        {
          "group": "com.google.zxing",
          "module": "core",
          "version": {
            "requires": "3.5.0"
          }
        },
        {
          "group": "com.localebro",
          "module": "okhttpprofiler",
          "version": {
            "requires": "1.0.8"
          }
        },
        {
          "group": "org.jetbrains.kotlinx",
          "module": "kotlinx-coroutines-core",
          "version": {
            "requires": "1.6.4"
          }
        },
        {
          "group": "org.jetbrains.kotlinx",
          "module": "kotlinx-coroutines-android",
          "version": {
            "requires": "1.6.4"
          }
        },
        {
          "group": "com.squareup.okio",
          "module": "okio",
          "version": {
            "requires": "3.2.0"
          }
        },
        {
          "group": "androidx.room",
          "module": "room-runtime",
          "version": {
            "requires": "2.5.1"
          }
        },
        {
          "group": "androidx.room",
          "module": "room-ktx",
          "version": {
            "requires": "2.5.1"
          }
        },
        {
          "group": "androidx.multidex",
          "module": "multidex",
          "version": {
            "requires": "2.0.1"
          }
        },
        {
          "group": "com.airbnb.android",
          "module": "paris",
          "version": {
            "requires": "2.0.0"
          }
        },
        {
          "group": "com.google.android.exoplayer",
          "module": "exoplayer-core",
          "version": {
            "requires": "2.18.7"
          }
        },
        {
          "group": "com.google.android.exoplayer",
          "module": "exoplayer-dash",
          "version": {
            "requires": "2.18.7"
          }
        },
        {
          "group": "com.google.android.exoplayer",
          "module": "exoplayer-ui",
          "version": {
            "requires": "2.18.7"
          }
        },
        {
          "group": "com.google.android.exoplayer",
          "module": "extension-leanback",
          "version": {
            "requires": "2.18.7"
          }
        },
        {
          "group": "androidx.leanback",
          "module": "leanback",
          "version": {
            "requires": "1.0.0"
          }
        },
        {
          "group": "com.kaltura.player",
          "module": "tvplayer",
          "version": {
            "requires": "4.29.0"
          }
        },
        {
          "group": "com.github.MackHartley",
          "module": "RoundedProgressBar",
          "version": {
            "requires": "3.0.0"
          }
        },
        {
          "group": "androidx.media3",
          "module": "media3-exoplayer",
          "version": {
            "requires": "1.4.1"
          }
        },
        {
          "group": "androidx.media3",
          "module": "media3-exoplayer-dash",
          "version": {
            "requires": "1.4.1"
          }
        },
        {
          "group": "androidx.media3",
          "module": "media3-ui",
          "version": {
            "requires": "1.4.1"
          }
        },
        {
          "group": "com.github.xYinKio",
          "module": "ArcCircleProgressBar",
          "version": {
            "requires": "0.07-alpha"
          }
        },
        {
          "group": "androidx.databinding",
          "module": "viewbinding",
          "version": {
            "requires": "8.1.1"
          }
        },
        {
          "group": "androidx.databinding",
          "module": "databinding-common",
          "version": {
            "requires": "8.1.1"
          }
        },
        {
          "group": "androidx.databinding",
          "module": "databinding-runtime",
          "version": {
            "requires": "8.1.1"
          }
        },
        {
          "group": "androidx.databinding",
          "module": "databinding-adapters",
          "version": {
            "requires": "8.1.1"
          }
        },
        {
          "group": "androidx.databinding",
          "module": "databinding-ktx",
          "version": {
            "requires": "8.1.1"
          }
        }
      ],
      "files": [
        {
          "name": "inthegametv-2.6.20.aar",
          "url": "inthegametv-2.6.20.aar",
          "size": 4976764,
          "sha512": "20014c30f9f2972c742ccae6153dfc328a350c9b168c89de8c579b960b4c42298edd878ca3eb7da74e7e1e8efdd51fb1a2ad6cc3d40d737bded8cd63f48e0b49",
          "sha256": "411fd11f583ea9f6db73fd375340fe1b066677b8f164a66b91b400caa0024d6d",
          "sha1": "92567e21bd616b9db9e4a6cbfd5884b488e99ab6",
          "md5": "54771ab2a96749210a2dc8ae970ae937"
        }
      ]
    },
    {
      "name": "releaseSourcesElements-published",
      "attributes": {
        "org.gradle.category": "documentation",
        "org.gradle.dependency.bundling": "external",
        "org.gradle.docstype": "sources",
        "org.gradle.libraryelements": "jar",
        "org.gradle.usage": "java-runtime",
        "org.jetbrains.kotlin.platform.type": "androidJvm"
      },
      "files": [
        {
          "name": "inthegametv-2.6.20-sources.jar",
          "url": "inthegametv-2.6.20-sources.jar",
          "size": 919565,
          "sha512": "d525376397858bb08bfd846bb4afbe64a2f60c56da78724c4b2fe36419c795944824323be5a9a253e45a1fb28e6a8c910b8582cf9a11d46f0f11fdbee1bf7ca7",
          "sha256": "827e1799ad5a6b22a9b444ba6fd242ef38fe055269daf215d5c71a6592908f31",
          "sha1": "ef5acded4c2ca5abc4b36fe86b1d3d14d4c3a73e",
          "md5": "4fa54318c06ea8cc2af27b13f0b587d6"
        }
      ]
    }
  ]
}
