{
  "formatVersion": "1.1",
  "component": {
    "group": "com.syncedapps",
    "module": "inthegametv",
    "version": "2.1.0",
    "attributes": {
      "org.gradle.status": "release"
    }
  },
  "createdBy": {
    "gradle": {
      "version": "7.4"
    }
  },
  "variants": [
    {
      "name": "releaseApiElements-published",
      "attributes": {
        "org.gradle.category": "library",
        "org.gradle.usage": "java-api",
        "org.jetbrains.kotlin.platform.type": "androidJvm"
      },
      "dependencies": [
        {
          "group": "com.github.Inthegamesdk",
          "module": "androidStorket",
          "version": {
            "requires": "1.0.11"
          }
        },
        {
          "group": "org.jetbrains.kotlin",
          "module": "kotlin-stdlib",
          "version": {
            "requires": "1.7.20"
          }
        },
        {
          "group": "org.jetbrains.kotlin",
          "module": "kotlin-stdlib-jdk7",
          "version": {
            "requires": "1.7.20"
          }
        },
        {
          "group": "org.jetbrains.kotlin",
          "module": "kotlin-stdlib-jdk8",
          "version": {
            "requires": "1.7.20"
          }
        },
        {
          "group": "androidx.fragment",
          "module": "fragment-ktx",
          "version": {
            "requires": "1.5.4"
          }
        },
        {
          "group": "androidx.activity",
          "module": "activity-ktx",
          "version": {
            "requires": "1.6.1"
          }
        },
        {
          "group": "androidx.core",
          "module": "core-ktx",
          "version": {
            "requires": "1.9.0"
          }
        },
        {
          "group": "androidx.appcompat",
          "module": "appcompat",
          "version": {
            "requires": "1.5.1"
          }
        },
        {
          "group": "com.google.android.material",
          "module": "material",
          "version": {
            "requires": "1.6.1"
          }
        },
        {
          "group": "com.squareup.retrofit2",
          "module": "retrofit",
          "version": {
            "requires": "2.9.0"
          },
          "excludes": [
            {
              "group": "com.squareup.okhttp3",
              "module": "okhttp"
            }
          ]
        },
        {
          "group": "com.squareup.retrofit2",
          "module": "converter-gson",
          "version": {
            "requires": "2.9.0"
          }
        },
        {
          "group": "com.google.android.flexbox",
          "module": "flexbox",
          "version": {
            "requires": "3.0.0"
          }
        },
        {
          "group": "com.github.bumptech.glide",
          "module": "glide",
          "version": {
            "requires": "4.13.2"
          }
        },
        {
          "group": "androidx.constraintlayout",
          "module": "constraintlayout",
          "version": {
            "requires": "2.1.4"
          }
        },
        {
          "group": "com.pusher",
          "module": "pusher-java-client",
          "version": {
            "requires": "2.2.6"
          }
        },
        {
          "group": "com.google.zxing",
          "module": "core",
          "version": {
            "requires": "3.5.0"
          }
        },
        {
          "group": "com.localebro",
          "module": "okhttpprofiler",
          "version": {
            "requires": "1.0.8"
          }
        },
        {
          "group": "org.jetbrains.kotlinx",
          "module": "kotlinx-coroutines-core",
          "version": {
            "requires": "1.6.4"
          }
        },
        {
          "group": "org.jetbrains.kotlinx",
          "module": "kotlinx-coroutines-android",
          "version": {
            "requires": "1.6.4"
          }
        },
        {
          "group": "com.squareup.okio",
          "module": "okio",
          "version": {
            "requires": "3.0.0"
          }
        },
        {
          "group": "androidx.room",
          "module": "room-runtime",
          "version": {
            "requires": "2.4.3"
          }
        },
        {
          "group": "androidx.room",
          "module": "room-ktx",
          "version": {
            "requires": "2.4.3"
          }
        },
        {
          "group": "androidx.multidex",
          "module": "multidex",
          "version": {
            "requires": "2.0.1"
          }
        },
        {
          "group": "com.airbnb.android",
          "module": "paris",
          "version": {
            "requires": "2.0.0"
          }
        },
        {
          "group": "com.google.android.exoplayer",
          "module": "exoplayer-core",
          "version": {
            "requires": "2.18.1"
          }
        },
        {
          "group": "com.google.android.exoplayer",
          "module": "exoplayer-dash",
          "version": {
            "requires": "2.18.1"
          }
        },
        {
          "group": "com.google.android.exoplayer",
          "module": "exoplayer-ui",
          "version": {
            "requires": "2.18.1"
          }
        },
        {
          "group": "androidx.databinding",
          "module": "viewbinding",
          "version": {
            "requires": "7.3.1"
          }
        }
      ],
      "files": [
        {
          "name": "inthegametv-2.1.0.aar",
          "url": "inthegametv-2.1.0.aar",
          "size": 4569750,
          "sha512": "1528f2f8f2e5d9e32302ef764c90b4591e53428a31f397a1867716f3899ef96859dedeefe3a3dd636403119da2a7bebe9e5a3ec1820f03911495f6f9b006256d",
          "sha256": "19c1151f0203a14048021bc391c638d4f3823805287aede1eefb22506495c456",
          "sha1": "cf2fdd0a57194f25e8dd28599319025554332a64",
          "md5": "7a840c3b1f17af21c96af9b9eabeaa3c"
        }
      ]
    },
    {
      "name": "releaseRuntimeElements-published",
      "attributes": {
        "org.gradle.category": "library",
        "org.gradle.usage": "java-runtime",
        "org.jetbrains.kotlin.platform.type": "androidJvm"
      },
      "dependencies": [
        {
          "group": "org.jetbrains.kotlin",
          "module": "kotlin-parcelize-runtime",
          "version": {
            "requires": "1.7.20"
          }
        },
        {
          "group": "com.github.Inthegamesdk",
          "module": "androidStorket",
          "version": {
            "requires": "1.0.11"
          }
        },
        {
          "group": "org.jetbrains.kotlin",
          "module": "kotlin-stdlib",
          "version": {
            "requires": "1.7.20"
          }
        },
        {
          "group": "org.jetbrains.kotlin",
          "module": "kotlin-stdlib-jdk7",
          "version": {
            "requires": "1.7.20"
          }
        },
        {
          "group": "org.jetbrains.kotlin",
          "module": "kotlin-stdlib-jdk8",
          "version": {
            "requires": "1.7.20"
          }
        },
        {
          "group": "androidx.fragment",
          "module": "fragment-ktx",
          "version": {
            "requires": "1.5.4"
          }
        },
        {
          "group": "androidx.activity",
          "module": "activity-ktx",
          "version": {
            "requires": "1.6.1"
          }
        },
        {
          "group": "androidx.core",
          "module": "core-ktx",
          "version": {
            "requires": "1.9.0"
          }
        },
        {
          "group": "androidx.appcompat",
          "module": "appcompat",
          "version": {
            "requires": "1.5.1"
          }
        },
        {
          "group": "com.google.android.material",
          "module": "material",
          "version": {
            "requires": "1.6.1"
          }
        },
        {
          "group": "com.squareup.retrofit2",
          "module": "retrofit",
          "version": {
            "requires": "2.9.0"
          },
          "excludes": [
            {
              "group": "com.squareup.okhttp3",
              "module": "okhttp"
            }
          ]
        },
        {
          "group": "com.squareup.retrofit2",
          "module": "converter-gson",
          "version": {
            "requires": "2.9.0"
          }
        },
        {
          "group": "com.google.android.flexbox",
          "module": "flexbox",
          "version": {
            "requires": "3.0.0"
          }
        },
        {
          "group": "com.github.bumptech.glide",
          "module": "glide",
          "version": {
            "requires": "4.13.2"
          }
        },
        {
          "group": "androidx.constraintlayout",
          "module": "constraintlayout",
          "version": {
            "requires": "2.1.4"
          }
        },
        {
          "group": "com.pusher",
          "module": "pusher-java-client",
          "version": {
            "requires": "2.2.6"
          }
        },
        {
          "group": "com.google.zxing",
          "module": "core",
          "version": {
            "requires": "3.5.0"
          }
        },
        {
          "group": "com.localebro",
          "module": "okhttpprofiler",
          "version": {
            "requires": "1.0.8"
          }
        },
        {
          "group": "org.jetbrains.kotlinx",
          "module": "kotlinx-coroutines-core",
          "version": {
            "requires": "1.6.4"
          }
        },
        {
          "group": "org.jetbrains.kotlinx",
          "module": "kotlinx-coroutines-android",
          "version": {
            "requires": "1.6.4"
          }
        },
        {
          "group": "com.squareup.okio",
          "module": "okio",
          "version": {
            "requires": "3.0.0"
          }
        },
        {
          "group": "androidx.room",
          "module": "room-runtime",
          "version": {
            "requires": "2.4.3"
          }
        },
        {
          "group": "androidx.room",
          "module": "room-ktx",
          "version": {
            "requires": "2.4.3"
          }
        },
        {
          "group": "androidx.multidex",
          "module": "multidex",
          "version": {
            "requires": "2.0.1"
          }
        },
        {
          "group": "com.airbnb.android",
          "module": "paris",
          "version": {
            "requires": "2.0.0"
          }
        },
        {
          "group": "com.google.android.exoplayer",
          "module": "exoplayer-core",
          "version": {
            "requires": "2.18.1"
          }
        },
        {
          "group": "com.google.android.exoplayer",
          "module": "exoplayer-dash",
          "version": {
            "requires": "2.18.1"
          }
        },
        {
          "group": "com.google.android.exoplayer",
          "module": "exoplayer-ui",
          "version": {
            "requires": "2.18.1"
          }
        },
        {
          "group": "androidx.databinding",
          "module": "viewbinding",
          "version": {
            "requires": "7.3.1"
          }
        },
        {
          "group": "androidx.swiperefreshlayout",
          "module": "swiperefreshlayout",
          "version": {
            "requires": "1.1.0"
          }
        }
      ],
      "files": [
        {
          "name": "inthegametv-2.1.0.aar",
          "url": "inthegametv-2.1.0.aar",
          "size": 4569750,
          "sha512": "1528f2f8f2e5d9e32302ef764c90b4591e53428a31f397a1867716f3899ef96859dedeefe3a3dd636403119da2a7bebe9e5a3ec1820f03911495f6f9b006256d",
          "sha256": "19c1151f0203a14048021bc391c638d4f3823805287aede1eefb22506495c456",
          "sha1": "cf2fdd0a57194f25e8dd28599319025554332a64",
          "md5": "7a840c3b1f17af21c96af9b9eabeaa3c"
        }
      ]
    }
  ]
}
